tcpcon/__main__.py
tcpcon/args.py
tcpcon/keyboard.py
tcpcon/network.py
tcpcon/tcp.py
tcpcon/terminate.py
tcpcon/version.py
tests/test_version.py
tcpcon-0.0.3.dist-info/LICENSE
tcpcon-0.0.3.dist-info/METADATA
tcpcon-0.0.3.dist-info/WHEEL
tcpcon-0.0.3.dist-info/entry_points.txt
tcpcon-0.0.3.dist-info/top_level.txt
tcpcon-0.0.3.dist-info/RECORD
