Metadata-Version: 2.1
Name: tcpcon
Version: 0.0.3
Summary: Command line utility to test tcp connections
Home-page: https://github.com/joaompinto/tcpcon
Author: João Pinto
Author-email: lamego.pinto@gmail.com
License: MIT
Platform: UNKNOWN
License-File: LICENSE
Requires-Dist: py-getch
